[
{"name":"Авдіївка","state":"Донецька область"},
{"name": "Алмазна","state":"Луганська область"},
{"name": "Алупка","state":"Крим"},
{"name": "Алушта","state":"Крим"},
{"name": "Алчевськ","state":"Луганська область"},
{"name": "Амвросіївка","state":"Донецька область"},
{"name": "Ананьїв","state":"Одеська область"},
{"name": "Андрушівка","state":"Житомирська область"},
{"name": "Антрацит","state":"Луганська область"},
{"name": "Апостолове","state":"Дніпропетровська область"},
{"name": "Армянськ","state":"Крим"},
{"name": "Арциз","state":"Одеська область"},
{"name": "Балаклія","state":"Харківська область"},
{"name": "Балта","state":"Одеська область"},
{"name": "Бар","state":"Вінницька область"},
{"name": "Баранівка","state":"Житомирська область"},
{"name": "Барвінкове","state":"Харківська область"},
{"name": "Батурин","state":"Чернігівська область"},
{"name": "Бахмач","state":"Чернігівська область"},
{"name": "Бахмут","state":"Донецька область"},
{"name": "Бахчисарай","state":"Крим"},
{"name": "Баштанка","state":"Миколаївська область"},
{"name": "Белз","state":"Львівська область"},
{"name": "Бердичів","state":"Житомирська область"},
{"name": "Бердянськ","state":"Запорізька область"},
{"name": "Берегове","state":"Закарпатська область"},
{"name": "Бережани","state":"Тернопільська область"},
{"name": "Березань","state":"Київська область"},
{"name": "Березівка","state":"Одеська область"},
{"name": "Березне","state":"Рівненська область"},
{"name": "Берестечко","state":"Волинська область"},
{"name": "Берислав","state":"Херсонська область"},
{"name": "Бершадь","state":"Вінницька область"},
{"name": "Бібрка","state":"Львівська область"},
{"name": "Біла Церква","state":"Київська область"},
{"name": "Білгород-Дністровський","state":"Одеська область"},
{"name": "Білицьке","state":"Донецька область"},
{"name": "Білогірськ","state":"Крим"},
{"name": "Білозерське","state":"Донецька область"},
{"name": "Білопілля","state":"Сумська область"},
{"name": "Біляївка","state":"Одеська область"},
{"name": "Благовіщенське","state":"Кіровоградська область"},
{"name": "Бобринець","state":"Кіровоградська область"},
{"name": "Бобровиця","state":"Чернігівська область"},
{"name": "Богодухів","state":"Харківська область"},
{"name": "Богуслав","state":"Київська область"},
{"name": "Боково-Хрустальне","state":"Луганська область"},
{"name": "Болград","state":"Одеська область"},
{"name": "Болехів","state":"Івано-Франківська область"},
{"name": "Борзна","state":"Чернігівська область"},
{"name": "Борислав","state":"Львівська область"},
{"name": "Бориспіль","state":"Київська область"},
{"name": "Борщів","state":"Тернопільська область"},
{"name": "Боярка","state":"Київська область"},
{"name": "Бровари","state":"Київська область"},
{"name": "Броди","state":"Львівська область"},
{"name": "Брянка","state":"Луганська область"},
{"name": "Бунге","state":"Донецька область"},
{"name": "Буринь","state":"Сумська область"},
{"name": "Бурштин","state":"Івано-Франківська область"},
{"name": "Буськ","state":"Львівська область"},
{"name": "Буча","state":"Київська область"},
{"name": "Бучач","state":"Тернопільська область"},
{"name": "Валки","state":"Харківська область"},
{"name": "Вараш","state":"Рівненська область"},
{"name": "Василівка","state":"Запорізька область"},
{"name": "Васильків","state":"Київська область"},
{"name": "Ватутіне","state":"Черкаська область"},
{"name": "Вашківці","state":"Чернівецька область"},
{"name": "Великі Мости","state":"Львівська область"},
{"name": "Верхівцеве","state":"Дніпропетровська область"},
{"name": "Верхньодніпровськ","state":"Дніпропетровська область"},
{"name": "Вижниця","state":"Чернівецька область"},
{"name": "Вилкове","state":"Одеська область"},
{"name": "Винники","state":"Львівська область"},
{"name": "Виноградів","state":"Закарпатська область"},
{"name": "Вишгород","state":"Київська область"},
{"name": "Вишневе","state":"Київська область"},
{"name": "Вільногірськ","state":"Дніпропетровська область"},
{"name": "Вільнянськ","state":"Запорізька область"},
{"name": "Вінниця","state":"Вінницька область"},
{"name": "Вовчанськ","state":"Харківська область"},
{"name": "Вознесенівка","state":"Луганська область"},
{"name": "Вознесенськ","state":"Миколаївська область"},
{"name": "Волноваха","state":"Донецька область"},
{"name": "Володимир","state":"Волинська область"},
{"name": "Волочиськ","state":"Хмельницька область"},
{"name": "Ворожба","state":"Сумська область"},
{"name": "Вуглегірськ","state":"Донецька область"},
{"name": "Вугледар","state":"Донецька область"},
{"name": "Гадяч","state":"Полтавська область"},
{"name": "Гайворон","state":"Кіровоградська область"},
{"name": "Гайсин","state":"Вінницька область"},
{"name": "Галич","state":"Івано-Франківська область"},
{"name": "Генічеськ","state":"Херсонська область"},
{"name": "Герца","state":"Чернівецька область"},
{"name": "Гірник","state":"Донецька область"},
{"name": "Гірське","state":"Луганська область"},
{"name": "Глиняни","state":"Львівська область"},
{"name": "Глобине","state":"Полтавська область"},
{"name": "Глухів","state":"Сумська область"},
{"name": "Гнівань","state":"Вінницька область"},
{"name": "Гола Пристань","state":"Херсонська область"},
{"name": "Голубівка","state":"Луганська область"},
{"name": "Горішні Плавні","state":"Полтавська область"},
{"name": "Горлівка","state":"Донецька область"},
{"name": "Городенка","state":"Івано-Франківська область"},
{"name": "Городище","state":"Черкаська область"},
{"name": "Городня","state":"Чернігівська область"},
{"name": "Городок","state":"Львівська область"},
{"name": "Городок","state":"Хмельницька область"},
{"name": "Горохів","state":"Волинська область"},
{"name": "Гребінка","state":"Полтавська область"},
{"name": "Гуляйполе","state":"Запорізька область"},
{"name": "Дебальцеве","state":"Донецька область"},
{"name": "Деражня","state":"Хмельницька область"},
{"name": "Дергачі","state":"Харківська область"},
{"name": "Джанкой","state":"Крим"},
{"name": "Дніпро","state":"Дніпропетровська область"},
{"name": "Дніпрорудне","state":"Запорізька область"},
{"name": "Добромиль","state":"Львівська область"},
{"name": "Добропілля","state":"Донецька область"},
{"name": "Довжанськ","state":"Луганська область"},
{"name": "Докучаєвськ","state":"Донецька область"},
{"name": "Долина","state":"Івано-Франківська область"},
{"name": "Долинська","state":"Кіровоградська область"},
{"name": "Донецьк","state":"Донецька область"},
{"name": "Дрогобич","state":"Львівська область"},
{"name": "Дружба","state":"Сумська область"},
{"name": "Дружківка","state":"Донецька область"},
{"name": "Дубляни","state":"Львівська область"},
{"name": "Дубно","state":"Рівненська область"},
{"name": "Дубровиця","state":"Рівненська область"},
{"name": "Дунаївці","state":"Хмельницька область"},
{"name": "Енергодар","state":"Запорізька область"},
{"name": "Євпаторія","state":"Крим"},
{"name": "Єнакієве","state":"Донецька область"},
{"name": "Жашків","state":"Черкаська область"},
{"name": "Жданівка","state":"Донецька область"},
{"name": "Жидачів","state":"Львівська область"},
{"name": "Житомир","state":"Житомирська область"},
{"name": "Жмеринка","state":"Вінницька область"},
{"name": "Жовква","state":"Львівська область"},
{"name": "Жовті Води","state":"Дніпропетровська область"},
{"name": "Заводське","state":"Полтавська область"},
{"name": "Залізне","state":"Донецька область"},
{"name": "Заліщики","state":"Тернопільська область"},
{"name": "Запоріжжя","state":"Запорізька область"},
{"name": "Заставна","state":"Чернівецька область"},
{"name": "Збараж","state":"Тернопільська область"},
{"name": "Зборів","state":"Тернопільська область"},
{"name": "Звенигородка","state":"Черкаська область"},
{"name": "Звягель","state":"Житомирська область"},
{"name": "Здолбунів","state":"Рівненська область"},
{"name": "Зеленодольськ","state":"Дніпропетровська область"},
{"name": "Зимогір","state":"'яЛуганська область"},
{"name": "Зіньків","state":"Полтавська область"},
{"name": "Зміїв","state":"Харківська область"},
{"name": "Знам'янка","state":"Кіровоградська область"},
{"name": "Золоте","state":"Луганська область"},
{"name": "Золотоноша","state":"Черкаська область"},
{"name": "Золочів","state":"Львівська область"},
{"name": "Зоринськ","state":"Луганська область"},
{"name": "Зугрес","state":"Донецька область"},
{"name": "Івано-Франківськ","state":"Івано-Франківська область"},
{"name": "Ізмаїл","state":"Одеська область"},
{"name": "Ізюм","state":"Харківська область"},
{"name": "Ізяслав","state":"Хмельницька область"},
{"name": "Іллінці","state":"Вінницька область"},
{"name": "Іловайськ","state":"Донецька область"},
{"name": "Інкерман","state":"Крим"},
{"name": "Ірміно","state":"Луганська область"},
{"name": "Ірпінь","state":"Київська область"},
{"name": "Іршава","state":"Закарпатська область"},
{"name": "Ічня","state":"Чернігівська область"},
{"name": "Кагарлик","state":"Київська область"},
{"name": "Кадіївка","state":"Луганська область"},
{"name": "Калинівка","state":"Вінницька область"},
{"name": "Калуш","state":"Івано-Франківська область"},
{"name": "Кальміуське","state":"Донецька область"},
{"name": "Камінь-Каширський","state":"Волинська область"},
{"name": "Кам'янець-Подільський","state":"Хмельницька область"},
{"name": "Кам'янка","state":"Черкаська область"},
{"name": "Кам'янка-Бузька","state":"Львівська область"},
{"name": "Кам'янка-Дніпровська","state":"Запорізька область"},
{"name": "Кам'янське","state":"Дніпропетровська область"},
{"name": "Канів","state":"Черкаська область"},
{"name": "Карлівка","state":"Полтавська область"},
{"name": "Каховка","state":"Херсонська область"},
{"name": "Керч","state":"Крим"},
{"name": "Київ","state":"Київська область"},
{"name": "Кипуче","state":"Луганська область"},
{"name": "Ківерці","state":"Волинська область"},
{"name": "Кілія","state":"Одеська область"},
{"name": "Кіцмань","state":"Чернівецька область"},
{"name": "Кобеляки","state":"Полтавська область"},
{"name": "Ковель","state":"Волинська область"},
{"name": "Кодима","state":"Одеська область"},
{"name": "Козятин","state":"Вінницька область"},
{"name": "Коломия","state":"Івано-Франківська область"},
{"name": "Комарно","state":"Львівська область"},
{"name": "Конотоп","state":"Сумська область"},
{"name": "Копичинці","state":"Тернопільська область"},
{"name": "Корець","state":"Рівненська область"},
{"name": "Коростень","state":"Житомирська область"},
{"name": "Коростишів","state":"Житомирська область"},
{"name": "Корсунь-Шевченківський","state":"Черкаська область"},
{"name": "Корюківка","state":"Чернігівська область"},
{"name": "Косів","state":"Івано-Франківська область"},
{"name": "Костопіль","state":"Рівненська область"},
{"name": "Костянтинівка","state":"Донецька область"},
{"name": "Краматорськ","state":"Донецька область"},
{"name": "Красилів","state":"Хмельницька область"},
{"name": "Красногорівка","state":"Донецька область"},
{"name": "Красноград","state":"Харківська область"},
{"name": "Кременець","state":"Тернопільська область"},
{"name": "Кременчук","state":"Полтавська область"},
{"name": "Кремінна","state":"Луганська область"},
{"name": "Кривий Ріг","state":"Дніпропетровська область"},
{"name": "Кролевець","state":"Сумська область"},
{"name": "Кропивницький","state":"Кіровоградська область"},
{"name": "Куп'янськ","state":"Харківська область"},
{"name": "Курахове","state":"Донецька область"},
{"name": "Ладижин","state":"Вінницька область"},
{"name": "Ланівці","state":"Тернопільська область"},
{"name": "Лебедин","state":"Сумська область"},
{"name": "Лиман","state":"Донецька область"},
{"name": "Липовець","state":"Вінницька область"},
{"name": "Лисичанськ","state":"Луганська область"},
{"name": "Лозова","state":"Харківська область"},
{"name": "Лохвиця","state":"Полтавська область"},
{"name": "Лубни","state":"Полтавська область"},
{"name": "Луганськ","state":"Луганська область"},
{"name": "Лутугине","state":"Луганська область"},
{"name": "Луцьк","state":"Волинська область"},
{"name": "Львів","state":"Львівська область"},
{"name": "Любомль","state":"Волинська область"},
{"name": "Люботин","state":"Харківська область"},
{"name": "Макіївка","state":"Донецька область"},
{"name": "Мала Виска","state":"Кіровоградська область"},
{"name": "Малин","state":"Житомирська область"},
{"name": "Марганець","state":"Дніпропетровська область"},
{"name": "Маріуполь","state":"Донецька область"},
{"name": "Мар'їнка","state":"Донецька область"},
{"name": "Мелітополь","state":"Запорізька область"},
{"name": "Мена","state":"Чернігівська область"},
{"name": "Мерефа","state":"Харківська область"},
{"name": "Миколаїв","state":"Львівська область"},
{"name": "Миколаїв","state":"Миколаївська область"},
{"name": "Миколаївка","state":"Донецька область"},
{"name": "Миргород","state":"Полтавська область"},
{"name": "Мирноград","state":"Донецька область"},
{"name": "Миронівка","state":"Київська область"},
{"name": "Міусинськ","state":"Луганська область"},
{"name": "Могилів-Подільський","state":"Вінницька область"},
{"name": "Молодогвардійськ","state":"Луганська область"},
{"name": "Молочанськ","state":"Запорізька область"},
{"name": "Монастириська","state":"Тернопільська область"},
{"name": "Монастирище","state":"Черкаська область"},
{"name": "Моршин","state":"Львівська область"},
{"name": "Моспине","state":"Донецька область"},
{"name": "Мостиська","state":"Львівська область"},
{"name": "Мукачево","state":"Закарпатська область"},
{"name": "Надвірна","state":"Івано-Франківська область"},
{"name": "Немирів","state":"Вінницька область"},
{"name": "Нетішин","state":"Хмельницька область"},
{"name": "Ніжин","state":"Чернігівська область"},
{"name": "Нікополь","state":"Дніпропетровська область"},
{"name": "Нова Каховка","state":"Херсонська область"},
{"name": "Нова Одеса","state":"Миколаївська область"},
{"name": "Новгород-Сіверський","state":"Чернігівська область"},
{"name": "Новий Буг","state":"Миколаївська область"},
{"name": "Новий Калинів","state":"Львівська область"},
{"name": "Новий Розділ","state":"Львівська область"},
{"name": "Новоазовськ","state":"Донецька область"},
{"name": "Нововолинськ","state":"Волинська область"},
{"name": "Новогродівка","state":"Донецька область"},
{"name": "Новодністровськ","state":"Чернівецька область"},
{"name": "Новодружеськ","state":"Луганська область"},
{"name": "Новомиргород","state":"Кіровоградська область"},
{"name": "Новомосковськ","state":"Дніпропетровська область"},
{"name": "Новоселиця","state":"Чернівецька область"},
{"name": "Новоукраїнка","state":"Кіровоградська область"},
{"name": "Новояворівськ","state":"Львівська область"},
{"name": "Носівка","state":"Чернігівська область"},
{"name": "Обухів","state":"Київська область"},
{"name": "Овруч","state":"Житомирська область"},
{"name": "Одеса","state":"Одеська область"},
{"name": "Олевськ","state":"Житомирська область"},
{"name": "Олександрівськ","state":"Луганська область"},
{"name": "Олександрія","state":"Кіровоградська область"},
{"name": "Олешки","state":"Херсонська область"},
{"name": "Оріхів","state":"Запорізька область"},
{"name": "Остер","state":"Чернігівська область"},
{"name": "Острог","state":"Рівненська область"},
{"name": "Охтирка","state":"Сумська область"},
{"name": "Очаків","state":"Миколаївська область"},
{"name": "Павлоград","state":"Дніпропетровська область"},
{"name": "Первомайськ","state":"Луганська область"},
{"name": "Первомайськ","state":"Миколаївська область"},
{"name": "Первомайський","state":"Харківська область"},
{"name": "Перевальськ","state":"Луганська область"},
{"name": "Перемишляни","state":"Львівська область"},
{"name": "Перечин","state":"Закарпатська область"},
{"name": "Перещепине","state":"Дніпропетровська область"},
{"name": "Переяслав","state":"Київська область"},
{"name": "Першотравенськ","state":"Дніпропетровська область"},
{"name": "Петрово-Красносілля","state":"Луганська область"},
{"name": "Пирятин","state":"Полтавська область"},
{"name": "Південне","state":"Харківська область"},
{"name": "Підгайці","state":"Тернопільська область"},
{"name": "Підгородне","state":"Дніпропетровська область"},
{"name": "Погребище","state":"Вінницька область"},
{"name": "Подільськ","state":"Одеська область"},
{"name": "Покров","state":"Дніпропетровська область"},
{"name": "Покровськ","state":"Донецька область"},
{"name": "Пологи","state":"Запорізька область"},
{"name": "Полонне","state":"Хмельницька область"},
{"name": "Полтава","state":"Полтавська область"},
{"name": "Помічна","state":"Кіровоградська область"},
{"name": "Попасна","state":"Луганська область"},
{"name": "Почаїв","state":"Тернопільська область"},
{"name": "Привілля","state":"Луганська область"},
{"name": "Прилуки","state":"Чернігівська область"},
{"name": "Приморськ","state":"Запорізька область"},
{"name": "Прип'ять","state":"Київська область"},
{"name": "Пустомити","state":"Львівська область"},
{"name": "Путивль","state":"Сумська область"},
{"name": "П'ятихатки","state":"Дніпропетровська область"},
{"name": "Рава-Руська","state":"Львівська область"},
{"name": "Радехів","state":"Львівська область"},
{"name": "Радивилів","state":"Рівненська область"},
{"name": "Радомишль","state":"Житомирська область"},
{"name": "Рахів","state":"Закарпатська область"},
{"name": "Рені","state":"Одеська область"},
{"name": "Решетилівка","state":"Полтавська область"},
{"name": "Ржищів","state":"Київська область"},
{"name": "Рівне","state":"Рівненська область"},
{"name": "Ровеньки","state":"Луганська область"},
{"name": "Рогатин","state":"Івано-Франківська область"},
{"name": "Родинське","state":"Донецька область"},
{"name": "Рожище","state":"Волинська область"},
{"name": "Роздільна","state":"Одеська область"},
{"name": "Ромни","state":"Сумська область"},
{"name": "Рубіжне","state":"Луганська область"},
{"name": "Рудки","state":"Львівська область"},
{"name": "Саки","state":"Крим"},
{"name": "Самбір","state":"Львівська область"},
{"name": "Сарни","state":"Рівненська область"},
{"name": "Свалява","state":"Закарпатська область"},
{"name": "Сватове","state":"Луганська область"},
{"name": "Світловодськ","state":"Кіровоградська область"},
{"name": "Світлодарськ","state":"Донецька область"},
{"name": "Святогірськ","state":"Донецька область"},
{"name": "Севастополь","state":"Крим"},
{"name": "Селидове","state":"Донецька область"},
{"name": "Семенівка","state":"Чернігівська область"},
{"name": "Середина-Буда","state":"Сумська область"},
{"name": "Сєвєродонецьк","state":"Луганська область"},
{"name": "Синельникове","state":"Дніпропетровська область"},
{"name": "Сіверськ","state":"Донецька область"},
{"name": "Сімферополь","state":"Крим"},
{"name": "Скадовськ","state":"Херсонська область"},
{"name": "Скалат","state":"Тернопільська область"},
{"name": "Сквира","state":"Київська область"},
{"name": "Сколе","state":"Львівська область"},
{"name": "Славута","state":"Хмельницька область"},
{"name": "Славутич","state":"Київська область"},
{"name": "Слов'янськ","state":"Донецька область"},
{"name": "Сміла","state":"Черкаська область"},
{"name": "Снігурівка","state":"Миколаївська область"},
{"name": "Сніжне","state":"Донецька область"},
{"name": "Сновськ","state":"Чернігівська область"},
{"name": "Снятин","state":"Івано-Франківська область"},
{"name": "Сокаль","state":"Львівська область"},
{"name": "Сокиряни","state":"Чернівецька область"},
{"name": "Соледар","state":"Донецька область"},
{"name": "Сорокине","state":"Луганська область"},
{"name": "Соснівка","state":"Львівська область"},
{"name": "Старий Крим","state":"Крим"},
{"name": "Старий Самбір","state":"Львівська область"},
{"name": "Старобільськ","state":"Луганська область"},
{"name": "Старокостянтинів","state":"Хмельницька область"},
{"name": "Стебник","state":"Львівська область"},
{"name": "Сторожинець","state":"Чернівецька область"},
{"name": "Стрий","state":"Львівська область"},
{"name": "Судак","state":"Крим"},
{"name": "Судова Вишня","state":"Львівська область"},
{"name": "Суми","state":"Сумська область"},
{"name": "Суходільськ","state":"Луганська область"},
{"name": "Таврійськ","state":"Херсонська область"},
{"name": "Тальне","state":"Черкаська область"},
{"name": "Тараща","state":"Київська область"},
{"name": "Татарбунари","state":"Одеська область"},
{"name": "Теплодар","state":"Одеська область"},
{"name": "Теребовля","state":"Тернопільська область"},
{"name": "Тернівка","state":"Дніпропетровська область"},
{"name": "Тернопіль","state":"Тернопільська область"},
{"name": "Тетіїв","state":"Київська область"},
{"name": "Тисмениця","state":"Івано-Франківська область"},
{"name": "Тлумач","state":"Івано-Франківська область"},
{"name": "Токмак","state":"Запорізька область"},
{"name": "Торецьк","state":"Донецька область"},
{"name": "Тростянець","state":"Сумська область"},
{"name": "Трускавець","state":"Львівська область"},
{"name": "Тульчин","state":"Вінницька область"},
{"name": "Турка","state":"Львівська область"},
{"name": "Тячів","state":"Закарпатська область"},
{"name": "Угнів","state":"Львівська область"},
{"name": "Ужгород","state":"Закарпатська область"},
{"name": "Узин","state":"Київська область"},
{"name": "Українка","state":"Київська область"},
{"name": "Українськ","state":"Донецька область"},
{"name": "Умань","state":"Черкаська область"},
{"name": "Устилуг","state":"Волинська область"},
{"name": "Фастів","state":"Київська область"},
{"name": "Феодосія","state":"Крим"},
{"name": "Харків","state":"Харківська область"},
{"name": "Харцизьк","state":"Донецька область"},
{"name": "Херсон","state":"Херсонська область"},
{"name": "Хирів","state":"Львівська область"},
{"name": "Хмельницький","state":"Хмельницька область"},
{"name": "Хмільник","state":"Вінницька область"},
{"name": "Ходорів","state":"Львівська область"},
{"name": "Хорол","state":"Полтавська область"},
{"name": "Хоростків","state":"Тернопільська область"},
{"name": "Хотин","state":"Чернівецька область"},
{"name": "Хрестівка","state":"Донецька область"},
{"name": "Христинівка","state":"Черкаська область"},
{"name": "Хрустальний","state":"Луганська область"},
{"name": "Хуст","state":"Закарпатська область"},
{"name": "Часів Яр","state":"Донецька область"},
{"name": "Червоноград","state":"Львівська область"},
{"name": "Черкаси","state":"Черкаська область"},
{"name": "Чернівці","state":"Чернівецька область"},
{"name": "Чернігів","state":"Чернігівська область"},
{"name": "Чигирин","state":"Черкаська область"},
{"name": "Чистякове","state":"Донецька область"},
{"name": "Чоп","state":"Закарпатська область"},
{"name": "Чорнобиль","state":"Київська область"},
{"name": "Чорноморськ","state":"Одеська область"},
{"name": "Чортків","state":"Тернопільська область"},
{"name": "Чугуїв","state":"Харківська область"},
{"name": "Чуднів","state":"Житомирська область"},
{"name": "Шаргород","state":"Вінницька область"},
{"name": "Шахтарськ","state":"Донецька область"},
{"name": "Шепетівка","state":"Хмельницька область"},
{"name": "Шостка","state":"Сумська область"},
{"name": "Шпола","state":"Черкаська область"},
{"name": "Шумськ","state":"Тернопільська область"},
{"name": "Щастя","state":"Луганська область"},
{"name": "Щолкіне","state":"Крим"},
{"name": "Южне","state":"Одеська область"},
{"name": "Южноукраїнськ","state":"Миколаївська область"},
{"name": "Яворів","state":"Львівська область"},
{"name": "Яготин","state":"Київська область"},
{"name": "Ялта","state":"Крим"},
{"name": "Ямпіль","state":"Вінницька область"},
{"name": "Яремче","state":"Івано-Франківська область"},
{"name": "Яни Капу","state":"Крим"},
{"name": "Ясинувата","state":"Донецька область"}
]